README.txt
setup.py
gse/__init__.py
gse/__main__.py
gse/config.py
gse/guide.py
gse/magma2.py
gse.egg-info/PKG-INFO
gse.egg-info/SOURCES.txt
gse.egg-info/dependency_links.txt
gse.egg-info/entry_points.txt
gse.egg-info/requires.txt
gse.egg-info/top_level.txt
gse.egg-info/zip-safe