Metadata-Version: 1.1
Name: gse
Version: 0.1.8
Summary: extract metadata and dataset from GEO Series Matrix format data
Home-page: http://pypi.python.org/pypi/gse/
Author: Nick Seidenman
Author-email: seidenman@wehi.edu.au
License: UNKNOWN
Keywords: dataset extraction metadata GSE bioinformatics
Platform: UNKNOWN
Classifier: Development Status :: 4 - Beta
Classifier: Environment :: Console
Classifier: Topic :: Scientific/Engineering :: Bio-Informatics
Classifier: Topic :: Scientific/Engineering :: Information Analysis
Classifier: License :: OSI Approved :: BSD License
